{
    "result": {
        "status": {
            "code": 0,
            "msg": "succ"
        },
        "timestamp": "Fri Jan 14 16:51:39 +0800 2022",
        "top": [],
        "pdps": [],
        "cre": [],
        "total": 12309,
        "end": 1641494894,
        "start": 1641540540,
        "lid": 2666,
        "rtime": 1642150299,
        "data": [
            {
                "oid": "489229654",
                "docid": "comos:kyamrmz3722914",
                "url": "https://finance.sina.com.cn/blockchain/roll/2022-01-07/doc-ikyamrmz3722914.shtml",
                "wapurl": "https://finance.sina.cn/forex/hsxw/2022-01-07/detail-ikyamrmz3722914.d.html",
                "title": "小米商城App已支持数字人民币支付",
                "stitle": "",
                "summary": "",
                "wapsummary": "",
                "intro": " 乐居财经讯 邓如菲1月7日消息，据新华财经报道，天星数科携手小米商城上线数字人民币支付服务，所有试点城市用户均可以在小米商城App使用数字人民币购买商品。",
                "ctime": "1641540540",
                "mtime": "1641543647",
                "intime": "1641543650",
                "author": "",
                "authoruid": "0",
                "level": "2",
                "img": {
                    "u": "http://n.sinaimg.cn/finance/transform/320/w640h480/20220107/c1ef-ed3c13c6f355dc121ecbfeccaf3e6787.jpg",
                    "w": "640",
                    "h": "480",
                    "t": ""
                },
                "images": [],
                "commentid": "cj:comos-kyamrmz3722914:0",
                "vid": "0",
                "ipad_vid": "0",
                "keywords": "小米商城,数字人民币,进出口,小米之家,雷军",
                "categoryid": "1",
                "channelid": "31",
                "mediaid": "0",
                "columnid": "1966,1972,60765,60810",
                "subjectid": "149281",
                "templateid": "0",
                "productid": "0",
                "lids": "295,1084,2487,2509,2519,2544,2666,2668,2676",
                "mlids": "",
                "ext_0": "0",
                "ext_1": "0",
                "ext_2": "0",
                "ext_3": "0",
                "ext_4": "0",
                "ext": "1",
                "media_name": "市场资讯",
                "video_id": "0",
                "video_time_length": "0",
                "urls": "[\"https:\\/\\/finance.sina.com.cn\\/blockchain\\/roll\\/2022-01-07\\/doc-ikyamrmz3722914.shtml\"]",
                "wapurls": "[\"https:\\/\\/finance.sina.cn\\/forex\\/hsxw\\/2022-01-07\\/detail-ikyamrmz3722914.d.html\",\"http:\\/\\/finance.sina.cn\\/forex\\/hsxw\\/2022-01-07\\/detail-ikyamrmz3722914.d.html\"]",
                "hqChart": "{\"stockCharts\":\"no\",\"stockCode\":\"\",\"stockMarket\":\"\",\"mulStockChart\":\"\",\"isStaticStock\":\"\"}",
                "icons": "",
                "is_cre_manual": "0"
            },
            {
                "oid": "489232954",
                "docid": "comos:kyakumx8891471",
                "url": "https://finance.sina.com.cn/blockchain/roll/2022-01-07/doc-ikyakumx8891471.shtml",
                "wapurl": "https://finance.sina.cn/blockchain/2022-01-07/detail-ikyakumx8891471.d.html",
                "title": "数字人民币APP上架引发体验热潮 美团平台数币用户日均增长18倍",
                "stitle": "",
                "summary": "",
                "wapsummary": "",
                "intro": "新年首个工作日，数字人民币试点版APP上架各大应用市场，“10+1”试点地区的用户不再需要邀请码即可体验数字人民币，旋即引发了用户体验热潮。",
                "ctime": "1641539640",
                "mtime": "1641542836",
                "intime": "1641542840",
                "author": "",
                "authoruid": "0",
                "level": "2",
                "img": {
                    "u": "http://n.sinaimg.cn/finance/transform/274/w543h531/20220107/26b8-32f16225074371e1fe664d2288598bc7.jpg",
                    "w": "543",
                    "h": "531",
                    "t": ""
                },
                "images": [
                    {
                        "u": "http://n.sinaimg.cn/spider20220107/274/w543h531/20220107/f086-604f6d65a99f07cd8dbff04ebd56c378.jpg",
                        "w": "543",
                        "h": "531",
                        "t": ""
                    }
                ],
                "commentid": "cj:comos-kyakumx8891471:0",
                "vid": "0",
                "ipad_vid": "0",
                "keywords": "数字人民币,APP,美团,美团外卖",
                "categoryid": "1",
                "channelid": "31",
                "mediaid": "0",
                "columnid": "60765,60810",
                "subjectid": "",
                "templateid": "0",
                "productid": "0",
                "lids": "2519,2544,2666,2668",
                "mlids": "",
                "ext_0": "0",
                "ext_1": "0",
                "ext_2": "0",
                "ext_3": "0",
                "ext_4": "0",
                "ext": "1",
                "media_name": "市场资讯",
                "video_id": "0",
                "video_time_length": "0",
                "urls": "[\"https:\\/\\/finance.sina.com.cn\\/blockchain\\/roll\\/2022-01-07\\/doc-ikyakumx8891471.shtml\"]",
                "wapurls": "[\"https:\\/\\/finance.sina.cn\\/blockchain\\/2022-01-07\\/detail-ikyakumx8891471.d.html\",\"http:\\/\\/finance.sina.cn\\/blockchain\\/2022-01-07\\/detail-ikyakumx8891471.d.html\"]",
                "comment_reply": "0",
                "comment_show": "1",
                "comment_total": "1",
                "praise": "0",
                "dispraise": "0",
                "hqChart": "{\"stockCharts\":\"no\",\"stockCode\":\"\",\"stockMarket\":\"\",\"mulStockChart\":\"\",\"isStaticStock\":\"\"}",
                "icons": "",
                "is_cre_manual": "0"
            },
            {
                "oid": "489224576",
                "docid": "comos:kyakumx8883845",
                "url": "https://finance.sina.com.cn/blockchain/roll/2022-01-07/doc-ikyakumx8883845.shtml",
                "wapurl": "https://finance.sina.cn/blockchain/2022-01-07/detail-ikyakumx8883845.d.html",
                "title": "皮鞋元宇宙来了 红蜻蜓申请元宇宙商标",
                "stitle": "",
                "summary": "",
                "wapsummary": "",
                "intro": " 天眼查APP显示，近日，浙江红蜻蜓鞋业股份有限公司申请注册“红蜻蜓元宇宙”商标，国际分类为教育娱乐、服装鞋帽，目前商标状态均为等待实质审查。",
                "ctime": "1641536957",
                "mtime": "1641541258",
                "intime": "1641541261",
                "author": "",
                "authoruid": "0",
                "level": "2",
                "img": {
                    "u": "http://n.sinaimg.cn/finance/transform/784/w640h144/20220107/82f9-332f9692b27e6fb568e6b3b0bd80156e.jpg",
                    "w": "640",
                    "h": "144",
                    "t": ""
                },
                "images": [
                    {
                        "u": "http://n.sinaimg.cn/spider20220107/784/w640h144/20220107/677e-b9e809698f75154470e1a25626e0e87b.jpg",
                        "w": "640",
                        "h": "144",
                        "t": ""
                    }
                ],
                "commentid": "cj:comos-kyakumx8883845:0",
                "vid": "0",
                "ipad_vid": "0",
                "keywords": "红蜻蜓,鞋业,浙江省,APP",
                "categoryid": "1",
                "channelid": "31",
                "mediaid": "0",
                "columnid": "60765,60808,60810",
                "subjectid": "",
                "templateid": "0",
                "productid": "0",
                "lids": "2519,2544,2666,2667,2668",
                "mlids": "",
                "ext_0": "0",
                "ext_1": "0",
                "ext_2": "0",
                "ext_3": "0",
                "ext_4": "0",
                "ext": "1",
                "media_name": "市场资讯",
                "video_id": "0",
                "video_time_length": "0",
                "urls": "[\"https:\\/\\/finance.sina.com.cn\\/blockchain\\/roll\\/2022-01-07\\/doc-ikyakumx8883845.shtml\"]",
                "wapurls": "[\"https:\\/\\/finance.sina.cn\\/blockchain\\/2022-01-07\\/detail-ikyakumx8883845.d.html\",\"http:\\/\\/finance.sina.cn\\/blockchain\\/2022-01-07\\/detail-ikyakumx8883845.d.html\"]",
                "hqChart": "{\"stockCharts\":\"no\",\"stockCode\":\"\",\"stockMarket\":\"\",\"mulStockChart\":\"\",\"isStaticStock\":\"\"}",
                "icons": "",
                "is_cre_manual": "0"
            },
            {
                "oid": "489228226",
                "docid": "comos:kyakumx8886609",
                "url": "https://finance.sina.com.cn/blockchain/roll/2022-01-07/doc-ikyakumx8886609.shtml",
                "wapurl": "https://finance.sina.cn/blockchain/2022-01-07/detail-ikyakumx8886609.d.html",
                "title": "噱头or趋势？打造数字员工 借势探路元宇宙",
                "stitle": "",
                "summary": "",
                "wapsummary": "",
                "intro": "原标题：银行打造数字员工 借势探路元宇宙 本报记者 张漫游 北京报道 借元宇宙概念大火之势，多个行业已经推出了数字员工，银行业也不例外。",
                "ctime": "1641536857",
                "mtime": "1641541661",
                "intime": "1641541664",
                "author": "",
                "authoruid": "0",
                "level": "2",
                "img": {
                    "u": "http://n.sinaimg.cn/finance/transform/566/w684h682/20220107/8bb9-4a7a3843acd8fbe1f2dbe1f1740d195d.jpg",
                    "w": "684",
                    "h": "682",
                    "t": ""
                },
                "images": [],
                "commentid": "cj:comos-kyakumx8886609:0",
                "vid": "0",
                "ipad_vid": "0",
                "keywords": "",
                "categoryid": "1",
                "channelid": "31",
                "mediaid": "0",
                "columnid": "60765,60808,60810",
                "subjectid": "",
                "templateid": "0",
                "productid": "0",
                "lids": "2519,2544,2666,2667,2668",
                "mlids": "",
                "ext_0": "0",
                "ext_1": "0",
                "ext_2": "0",
                "ext_3": "0",
                "ext_4": "0",
                "ext": "1",
                "media_name": "中国经营报",
                "video_id": "0",
                "video_time_length": "0",
                "urls": "[\"https:\\/\\/finance.sina.com.cn\\/blockchain\\/roll\\/2022-01-07\\/doc-ikyakumx8886609.shtml\"]",
                "wapurls": "[\"https:\\/\\/finance.sina.cn\\/blockchain\\/2022-01-07\\/detail-ikyakumx8886609.d.html\",\"http:\\/\\/finance.sina.cn\\/blockchain\\/2022-01-07\\/detail-ikyakumx8886609.d.html\"]",
                "hqChart": "{\"stockCharts\":\"no\",\"stockCode\":\"\",\"stockMarket\":\"\",\"mulStockChart\":\"\",\"isStaticStock\":\"\"}",
                "icons": "",
                "is_cre_manual": "0"
            },
            {
                "oid": "489224025",
                "docid": "comos:kyamrmz3705730",
                "url": "https://finance.sina.com.cn/blockchain/roll/2022-01-07/doc-ikyamrmz3705730.shtml",
                "wapurl": "https://finance.sina.cn/blockchain/2022-01-07/detail-ikyamrmz3705730.d.html",
                "title": "“日化老大”宝洁的美容元宇宙 和蚂蚁森林差不多功能",
                "stitle": "",
                "summary": "",
                "wapsummary": "",
                "intro": "记者 | 周芳颖编辑 | 楼婍沁1 以日化产品为核心的P&amp;G（Procter &amp; Gamble）宝洁集团正不断加大在美妆领域的投入。 1月4日，据《女装日报》报道...",
                "ctime": "1641535484",
                "mtime": "1641541329",
                "intime": "1641541334",
                "author": "",
                "authoruid": "0",
                "level": "2",
                "img": {
                    "u": "http://n.sinaimg.cn/finance/transform/621/w910h511/20220107/8f78-fcd4912abc8f8278881e57802794cf75.jpg",
                    "w": "910",
                    "h": "511",
                    "t": ""
                },
                "images": [
                    {
                        "u": "http://n.sinaimg.cn/sinakd20220107s/621/w910h511/20220107/802a-f57a8d3a351a91092504bc3aad80f8e8.jpg",
                        "w": "910",
                        "h": "511",
                        "t": "图片来源：TULA官网"
                    },
                    {
                        "u": "http://n.sinaimg.cn/sinakd20220107s/28/w2790h1238/20220107/1cf1-23da135495114fcd25d104d0499bff99.png",
                        "w": "2790",
                        "h": "1238",
                        "t": "图片来源：宝洁官网"
                    }
                ],
                "commentid": "cj:comos-kyamrmz3705730:0",
                "vid": "0",
                "ipad_vid": "0",
                "keywords": "女装日报",
                "categoryid": "1",
                "channelid": "31",
                "mediaid": "0",
                "columnid": "60765,60808,60810",
                "subjectid": "",
                "templateid": "0",
                "productid": "0",
                "lids": "2519,2544,2666,2667,2668",
                "mlids": "",
                "ext_0": "0",
                "ext_1": "0",
                "ext_2": "0",
                "ext_3": "0",
                "ext_4": "0",
                "ext": "1",
                "media_name": "界面",
                "video_id": "0",
                "video_time_length": "0",
                "urls": "[\"https:\\/\\/finance.sina.com.cn\\/blockchain\\/roll\\/2022-01-07\\/doc-ikyamrmz3705730.shtml\"]",
                "wapurls": "[\"https:\\/\\/finance.sina.cn\\/blockchain\\/2022-01-07\\/detail-ikyamrmz3705730.d.html\",\"http:\\/\\/finance.sina.cn\\/blockchain\\/2022-01-07\\/detail-ikyamrmz3705730.d.html\"]",
                "hqChart": "{\"stockCharts\":\"no\",\"stockCode\":\"\",\"stockMarket\":\"\",\"mulStockChart\":\"\",\"isStaticStock\":\"\"}",
                "icons": "",
                "is_cre_manual": "0"
            },
            {
                "oid": "489196387",
                "docid": "comos:kyamrmz3705279",
                "url": "https://finance.sina.com.cn/chanjing/gsnews/2022-01-07/doc-ikyamrmz3705279.shtml",
                "wapurl": "https://finance.sina.cn/2022-01-07/detail-ikyamrmz3705279.d.html",
                "title": "滚石音乐申请元宇宙商标",
                "stitle": "",
                "summary": "",
                "wapsummary": "",
                "intro": " 据天眼查App显示，近日，滚石国际音乐股份有限公司申请注册多个“滚石元宇宙”商标，国际分类含教育娱乐、科学仪器、办公用品，当前商标状态均为等待实质审查。",
                "ctime": "1641535369",
                "mtime": "1641541407",
                "intime": "1641541409",
                "author": "",
                "authoruid": "0",
                "level": "2",
                "img": {
                    "u": "http://n.sinaimg.cn/finance/transform/100/w1247h453/20220107/12c2-d852ad60742ba60ac116af25ce4ea3dc.png",
                    "w": "1247",
                    "h": "453",
                    "t": ""
                },
                "images": [
                    {
                        "u": "http://n.sinaimg.cn/sinakd20220107s/100/w1247h453/20220107/dbc3-4a65c578ebf1aa8c123fcd7033bd69d1.png",
                        "w": "1247",
                        "h": "453",
                        "t": ""
                    }
                ],
                "commentid": "cj:comos-kyamrmz3705279:0",
                "vid": "0",
                "ipad_vid": "0",
                "keywords": "",
                "categoryid": "1",
                "channelid": "31",
                "mediaid": "0",
                "columnid": "1908,1913,60765,60810",
                "subjectid": "",
                "templateid": "0",
                "productid": "0",
                "lids": "295,1081,1693,1694,2509,2516,2519,2544,2666,2668",
                "mlids": "",
                "ext_0": "0",
                "ext_1": "0",
                "ext_2": "0",
                "ext_3": "0",
                "ext_4": "0",
                "ext": "1",
                "media_name": "界面",
                "video_id": "0",
                "video_time_length": "0",
                "urls": "[\"https:\\/\\/finance.sina.com.cn\\/chanjing\\/gsnews\\/2022-01-07\\/doc-ikyamrmz3705279.shtml\"]",
                "wapurls": "[\"https:\\/\\/finance.sina.cn\\/2022-01-07\\/detail-ikyamrmz3705279.d.html\",\"http:\\/\\/finance.sina.cn\\/2022-01-07\\/detail-ikyamrmz3705279.d.html\"]",
                "hqChart": "{\"stockCharts\":\"no\",\"stockCode\":\"\",\"stockMarket\":\"\",\"mulStockChart\":\"\",\"isStaticStock\":\"\"}",
                "icons": "",
                "is_cre_manual": "0"
            },
            {
                "oid": "489234357",
                "docid": "comos:kyakumx8872744",
                "url": "https://finance.sina.com.cn/blockchain/roll/2022-01-07/doc-ikyakumx8872744.shtml",
                "wapurl": "https://finance.sina.cn/blockchain/2022-01-07/detail-ikyakumx8872744.d.html",
                "title": "普及数字人民币核心在于优化用户体验",
                "stitle": "",
                "summary": "",
                "wapsummary": "",
                "intro": "羊城晚报 □盘和林 1月4日，数字人民币（试点版）APP上线各大手机应用商城，虽然数字人民币APP依然限定试点城市使用，但是非试点城市的居民，也可以在应用商城下载APP...",
                "ctime": "1641532983",
                "mtime": "1641542752",
                "intime": "1641542754",
                "author": "",
                "authoruid": "0",
                "level": "2",
                "img": {
                    "u": "http://n.sinaimg.cn/finance/transform/764/w500h264/20220107/ffc6-4f691d6ade1fc3c4acc1fbfb364af6cf.jpg",
                    "w": "500",
                    "h": "264",
                    "t": ""
                },
                "images": [],
                "commentid": "cj:comos-kyakumx8872744:0",
                "vid": "0",
                "ipad_vid": "0",
                "keywords": "数字人民币,APP",
                "categoryid": "1",
                "channelid": "31",
                "mediaid": "0",
                "columnid": "60765,60810",
                "subjectid": "",
                "templateid": "0",
                "productid": "0",
                "lids": "2519,2544,2666,2668",
                "mlids": "",
                "ext_0": "0",
                "ext_1": "0",
                "ext_2": "0",
                "ext_3": "0",
                "ext_4": "0",
                "ext": "1",
                "media_name": "中国新闻网",
                "video_id": "0",
                "video_time_length": "0",
                "urls": "[\"https:\\/\\/finance.sina.com.cn\\/blockchain\\/roll\\/2022-01-07\\/doc-ikyakumx8872744.shtml\"]",
                "wapurls": "[\"https:\\/\\/finance.sina.cn\\/blockchain\\/2022-01-07\\/detail-ikyakumx8872744.d.html\",\"http:\\/\\/finance.sina.cn\\/blockchain\\/2022-01-07\\/detail-ikyakumx8872744.d.html\"]",
                "hqChart": "{\"stockCharts\":\"\\u5916\\u6c47K\\u7ebf\\u56fe\",\"stockCode\":\"USDCNY\",\"stockMarket\":\"\",\"mulStockChart\":\"\",\"isStaticStock\":\"\"}",
                "icons": "",
                "is_cre_manual": "0"
            },
            {
                "oid": "489226980",
                "docid": "comos:kyamrmz3687078",
                "url": "https://finance.sina.com.cn/blockchain/roll/2022-01-07/doc-ikyamrmz3687078.shtml",
                "wapurl": "https://finance.sina.cn/blockchain/2022-01-07/detail-ikyamrmz3687078.d.html",
                "title": "CES化身“元宇宙”技术展示场 各大厂商纷纷推出新品",
                "stitle": "",
                "summary": "",
                "wapsummary": "",
                "intro": "日前，CES 2022如期进行，众多科技公司，纷纷在元宇宙概念下，放出自家新品或新计划。 其中，高通和微软就宣布将会合作开发应用于AR眼镜的定制芯片...",
                "ctime": "1641527694",
                "mtime": "1641541434",
                "intime": "1641541436",
                "author": "",
                "authoruid": "0",
                "level": "2",
                "img": {
                    "u": "http://n.sinaimg.cn/finance/transform/739/w1080h459/20220107/4265-fcbc434003b24b3802a76183856f6e65.jpg",
                    "w": "1080",
                    "h": "459",
                    "t": ""
                },
                "images": [
                    {
                        "u": "http://n.sinaimg.cn/sinakd20220107s/100/w600h300/20220107/7718-29aba184a10d81434ec31f72969957f8.jpg",
                        "w": "600",
                        "h": "300",
                        "t": ""
                    }
                ],
                "commentid": "cj:comos-kyamrmz3687078:0",
                "vid": "0",
                "ipad_vid": "0",
                "keywords": "ces,三星",
                "categoryid": "1",
                "channelid": "31",
                "mediaid": "0",
                "columnid": "60765,60808,60810",
                "subjectid": "",
                "templateid": "0",
                "productid": "0",
                "lids": "2519,2544,2666,2667,2668",
                "mlids": "",
                "ext_0": "0",
                "ext_1": "0",
                "ext_2": "0",
                "ext_3": "0",
                "ext_4": "0",
                "ext": "1",
                "media_name": "市场资讯",
                "video_id": "0",
                "video_time_length": "0",
                "urls": "[\"https:\\/\\/finance.sina.com.cn\\/blockchain\\/roll\\/2022-01-07\\/doc-ikyamrmz3687078.shtml\"]",
                "wapurls": "[\"https:\\/\\/finance.sina.cn\\/blockchain\\/2022-01-07\\/detail-ikyamrmz3687078.d.html\",\"http:\\/\\/finance.sina.cn\\/blockchain\\/2022-01-07\\/detail-ikyamrmz3687078.d.html\"]",
                "hqChart": "{\"stockCharts\":\"no\",\"stockCode\":\"\",\"stockMarket\":\"\",\"mulStockChart\":\"\",\"isStaticStock\":\"\"}",
                "icons": "",
                "is_cre_manual": "0"
            },
            {
                "icons": "",
                "is_cre_manual": "0",
                "hqChart": "{\"stockCharts\":\"no\",\"stockCode\":\"\",\"stockMarket\":\"\",\"mulStockChart\":\"\",\"isStaticStock\":\"\"}",
                "intime": "1641695551",
                "channelid": "31",
                "ctime": "1641526743",
                "mtime": "1641695551",
                "authoruid": "0",
                "level": "2",
                "vid": "0",
                "ipad_vid": "0",
                "video_time_length": "0",
                "categoryid": "1",
                "mediaid": "0",
                "templateid": "0",
                "productid": "0",
                "ext_0": "0",
                "ext_1": "0",
                "ext_2": "0",
                "ext_3": "0",
                "ext_4": "0",
                "docid": "comos:kyamrmz3680143",
                "url": "https://finance.sina.com.cn/blockchain/roll/2022-01-07/doc-ikyamrmz3680143.shtml",
                "urls": "[\"https:\\/\\/finance.sina.com.cn\\/blockchain\\/roll\\/2022-01-07\\/doc-ikyamrmz3680143.shtml\"]",
                "wapurl": "https://finance.sina.cn/blockchain/2022-01-07/detail-ikyamrmz3680143.d.html",
                "wapurls": "[\"https:\\/\\/finance.sina.cn\\/blockchain\\/2022-01-07\\/detail-ikyamrmz3680143.d.html\",\"http:\\/\\/finance.sina.cn\\/blockchain\\/2022-01-07\\/detail-ikyamrmz3680143.d.html\"]",
                "wapsummary": "",
                "title": "小米支持数字人民币支付 小米商城APP与小米之家门店均可购买",
                "stitle": "",
                "summary": "",
                "intro": "近日，小米商城正式上线数字人民币支付服务。至此，由天星数科提供技术支持的数字人民币场景，已经完成了小米集团新零售线上线下全场景布局...",
                "author": "",
                "commentid": "cj:comos-kyamrmz3680143:0",
                "video_id": "",
                "keywords": "数字人民币,小米商城,数科,中国人民银行,数字货币",
                "media_name": "中国新闻网",
                "columnid": "60765,60810",
                "subjectid": "149281",
                "img": [],
                "images": [
                    {
                        "u": "http://n.sinaimg.cn/sinakd20220107s/199/w640h359/20220107/471a-52472cdd1a2a57f72d46ce19108b1d20.jpg",
                        "w": "640",
                        "h": "359",
                        "t": ""
                    }
                ],
                "lids": "2519,2544,2666,2668",
                "oid": "489230843",
                "comment_reply": 0,
                "comment_show": 0,
                "comment_total": 0
            },
            {
                "oid": "489146618",
                "docid": "comos:kyakumx8851447",
                "url": "https://finance.sina.com.cn/blockchain/roll/2022-01-07/doc-ikyakumx8851447.shtml",
                "wapurl": "https://finance.sina.cn/forex/hsxw/2022-01-07/detail-ikyakumx8851447.d.html",
                "title": "比特币跌破42000美元 为去年9月30日以来最低水平",
                "stitle": "",
                "summary": "",
                "wapsummary": "",
                "intro": "比特币日内下跌2.6%，报41932美元/枚，为去年9月30日以来最低水平。 全球最大的对冲基金桥水（Bridgewater Associates）创始人瑞·达利欧（Ray Dalio）重申了他的警告...",
                "ctime": "1641526400",
                "mtime": "1641543806",
                "intime": "1641543808",
                "author": "",
                "authoruid": "0",
                "level": "2",
                "img": [],
                "images": [
                    {
                        "u": "http://n.sinaimg.cn/finance/transform/639/w288h351/20220107/831b-1ccce306420c68559076951fb8ad3b11.png",
                        "w": "288",
                        "h": "351",
                        "t": ""
                    }
                ],
                "commentid": "cj:comos-kyakumx8851447:0",
                "vid": "0",
                "ipad_vid": "0",
                "keywords": "",
                "categoryid": "1",
                "channelid": "31",
                "mediaid": "0",
                "columnid": "1966,1972,60765,60810",
                "subjectid": "",
                "templateid": "0",
                "productid": "0",
                "lids": "295,1084,2487,2509,2519,2544,2666,2668,2676",
                "mlids": "",
                "ext_0": "0",
                "ext_1": "0",
                "ext_2": "0",
                "ext_3": "0",
                "ext_4": "0",
                "ext": "1",
                "media_name": "市场资讯",
                "video_id": "0",
                "video_time_length": "0",
                "urls": "[\"https:\\/\\/finance.sina.com.cn\\/blockchain\\/roll\\/2022-01-07\\/doc-ikyakumx8851447.shtml\"]",
                "wapurls": "[\"https:\\/\\/finance.sina.cn\\/forex\\/hsxw\\/2022-01-07\\/detail-ikyakumx8851447.d.html\",\"http:\\/\\/finance.sina.cn\\/forex\\/hsxw\\/2022-01-07\\/detail-ikyakumx8851447.d.html\"]",
                "comment_reply": "6",
                "comment_show": "5",
                "comment_total": "16",
                "praise": "0",
                "dispraise": "0",
                "hqChart": "{\"stockCharts\":\"\\u6bd4\\u7279\\u5e01k\\u7ebf\\u56fe\",\"stockCode\":\"btcbtcdollar\",\"stockMarket\":\"no\",\"mulStockChart\":\"\",\"isStaticStock\":\"\"}",
                "icons": "",
                "is_cre_manual": "0"
            },
            {
                "oid": "489129625",
                "docid": "comos:kyamrmz3669146",
                "url": "https://finance.sina.com.cn/blockchain/roll/2022-01-07/doc-ikyamrmz3669146.shtml",
                "wapurl": "https://finance.sina.cn/blockchain/2022-01-07/detail-ikyamrmz3669146.d.html",
                "title": "谁能带领 NFT 走出 Opensea？",
                "stitle": "",
                "summary": "",
                "wapsummary": "",
                "intro": "作者：许志宏 如果把加密世界比喻为一枚硬币的话，硬币正面是比特币这样的数字货币，那反面便是承载非标准资产的 NFT。它可以是代表社区身份标识的无聊猿头像（The Bored...",
                "ctime": "1641524027",
                "mtime": "1641524338",
                "intime": "1641524341",
                "author": "",
                "authoruid": "0",
                "level": "2",
                "img": {
                    "u": "http://n.sinaimg.cn/finance/transform/367/w667h500/20220107/d921-6e9bf11e7496b55206617a217dd0dde8.jpg",
                    "w": "667",
                    "h": "500",
                    "t": ""
                },
                "images": [],
                "commentid": "cj:comos-kyamrmz3669146:0",
                "vid": "0",
                "ipad_vid": "0",
                "keywords": "",
                "categoryid": "1",
                "channelid": "31",
                "mediaid": "0",
                "columnid": "60765,60808,60810",
                "subjectid": "",
                "templateid": "0",
                "productid": "0",
                "lids": "2519,2544,2666,2667,2668",
                "mlids": "",
                "ext_0": "0",
                "ext_1": "0",
                "ext_2": "0",
                "ext_3": "0",
                "ext_4": "0",
                "ext": "1",
                "media_name": "市场资讯",
                "video_id": "0",
                "video_time_length": "0",
                "urls": "[\"https:\\/\\/finance.sina.com.cn\\/blockchain\\/roll\\/2022-01-07\\/doc-ikyamrmz3669146.shtml\"]",
                "wapurls": "[\"https:\\/\\/finance.sina.cn\\/blockchain\\/2022-01-07\\/detail-ikyamrmz3669146.d.html\",\"http:\\/\\/finance.sina.cn\\/blockchain\\/2022-01-07\\/detail-ikyamrmz3669146.d.html\"]",
                "hqChart": "{\"stockCharts\":\"\\u6bd4\\u7279\\u5e01k\\u7ebf\\u56fe\",\"stockCode\":\"btcbtcdollar\",\"stockMarket\":\"no\",\"mulStockChart\":\"\",\"isStaticStock\":\"\"}",
                "icons": "",
                "is_cre_manual": "0"
            },
            {
                "oid": "489167943",
                "docid": "comos:kyamrmz3691230",
                "url": "https://finance.sina.com.cn/jjxw/2022-01-07/doc-ikyamrmz3691230.shtml",
                "wapurl": "https://finance.sina.cn/2022-01-07/detail-ikyamrmz3691230.d.html",
                "title": "周杰伦“身陷”元宇宙",
                "stitle": "",
                "summary": "",
                "wapsummary": "",
                "intro": " 元旦期间，“周杰伦入局元宇宙，40分钟卖6200万元”的新闻登上微博热搜。而仅仅几天前，周杰伦才刚从合作十余年的“真爱范特西” KTV退股。",
                "ctime": "1641523080",
                "mtime": "1641541838",
                "intime": "1641541843",
                "author": "",
                "authoruid": "0",
                "level": "2",
                "img": {
                    "u": "http://n.sinaimg.cn/finance/transform/124/w1080h644/20220107/0074-48f08dd434673488ec0dd6507013caa2.png",
                    "w": "1080",
                    "h": "644",
                    "t": ""
                },
                "images": [
                    {
                        "u": "http://n.sinaimg.cn/spider20220107/124/w1080h644/20220107/1a19-49c518149479415acce729a7a81abce9.png",
                        "w": "1080",
                        "h": "644",
                        "t": ""
                    },
                    {
                        "u": "http://n.sinaimg.cn/spider20220107/324/w1080h1644/20220107/6206-6a96df76e828c019361f00f5b6406b2a.png",
                        "w": "1080",
                        "h": "1644",
                        "t": ""
                    },
                    {
                        "u": "http://n.sinaimg.cn/spider20220107/74/w1080h594/20220107/62af-a007f865f8a4462b4a972dacf85b5713.png",
                        "w": "1080",
                        "h": "594",
                        "t": ""
                    },
                    {
                        "u": "http://n.sinaimg.cn/spider20220107/698/w957h541/20220107/bc4c-29b3a08940c8d2bcdf4e4667096922ed.png",
                        "w": "957",
                        "h": "541",
                        "t": ""
                    }
                ],
                "commentid": "cj:comos-kyamrmz3691230:0",
                "vid": "0",
                "ipad_vid": "0",
                "keywords": "周杰伦,NFT",
                "categoryid": "1",
                "channelid": "31",
                "mediaid": "0",
                "columnid": "60765,60808,60810",
                "subjectid": "",
                "templateid": "0",
                "productid": "0",
                "lids": "2519,2544,2666,2667,2668",
                "mlids": "",
                "ext_0": "0",
                "ext_1": "0",
                "ext_2": "0",
                "ext_3": "0",
                "ext_4": "0",
                "ext": "1",
                "media_name": "市场资讯",
                "video_id": "0",
                "video_time_length": "0",
                "urls": "[\"https:\\/\\/finance.sina.com.cn\\/jjxw\\/2022-01-07\\/doc-ikyamrmz3691230.shtml\"]",
                "wapurls": "[\"https:\\/\\/finance.sina.cn\\/2022-01-07\\/detail-ikyamrmz3691230.d.html\",\"http:\\/\\/finance.sina.cn\\/2022-01-07\\/detail-ikyamrmz3691230.d.html\"]",
                "hqChart": "{\"stockCharts\":\"no\",\"stockCode\":\"\",\"stockMarket\":\"\",\"mulStockChart\":\"\",\"isStaticStock\":\"\"}",
                "icons": "",
                "is_cre_manual": "0"
            },
            {
                "oid": "489138918",
                "docid": "comos:kyakumx8831159",
                "url": "https://finance.sina.com.cn/blockchain/roll/2022-01-07/doc-ikyakumx8831159.shtml",
                "wapurl": "https://finance.sina.cn/blockchain/coin/2022-01-07/detail-ikyakumx8831159.d.html",
                "title": "达利欧：政府可能禁止比特币 把握市场时机“比在奥运会上比赛还难”",
                "stitle": "",
                "summary": "摘要：全球最大的对冲基金桥水（Bridgewater Associates）创始人瑞·达利欧（Ray Dalio）重申了他的警告，即政府可能会禁止比特币。试图把握市场时机是一件愚蠢的事，类似于在短跑比赛中击败尤塞恩·博尔特，或在泳池中击败迈克尔·菲尔普斯。",
                "wapsummary": "",
                "intro": " 比推消息，全球最大的对冲基金桥水（Bridgewater Associates）创始人瑞·达利欧（Ray Dalio）重申了他的警告，即政府可能会禁止比特币。",
                "ctime": "1641521347",
                "mtime": "1641526125",
                "intime": "1641526128",
                "author": "",
                "authoruid": "0",
                "level": "2",
                "img": {
                    "u": "http://n.sinaimg.cn/finance/transform/137/w600h337/20220107/66a6-a5321abceb7886c4cae78306bd3fc796.jpg",
                    "w": "600",
                    "h": "337",
                    "t": ""
                },
                "images": [
                    {
                        "u": "http://n.sinaimg.cn/spider20220107/137/w600h337/20220107/11f3-bc1747379a11b1467211b55f13a585f6.jpg",
                        "w": "600",
                        "h": "337",
                        "t": ""
                    },
                    {
                        "u": "http://n.sinaimg.cn/spider20220107/250/w600h450/20220107/a535-d4a555145647942257e5b7b3254e8d80.jpg",
                        "w": "600",
                        "h": "450",
                        "t": ""
                    }
                ],
                "commentid": "cj:comos-kyakumx8831159:0",
                "vid": "0",
                "ipad_vid": "0",
                "keywords": "",
                "categoryid": "1",
                "channelid": "31",
                "mediaid": "0",
                "columnid": "60765,60808,60810",
                "subjectid": "",
                "templateid": "0",
                "productid": "0",
                "lids": "2519,2544,2666,2667,2668",
                "mlids": "",
                "ext_0": "0",
                "ext_1": "0",
                "ext_2": "0",
                "ext_3": "0",
                "ext_4": "0",
                "ext": "1",
                "media_name": "市场资讯",
                "video_id": "0",
                "video_time_length": "0",
                "urls": "[\"https:\\/\\/finance.sina.com.cn\\/blockchain\\/roll\\/2022-01-07\\/doc-ikyakumx8831159.shtml\"]",
                "wapurls": "[\"https:\\/\\/finance.sina.cn\\/blockchain\\/coin\\/2022-01-07\\/detail-ikyakumx8831159.d.html\",\"http:\\/\\/finance.sina.cn\\/blockchain\\/coin\\/2022-01-07\\/detail-ikyakumx8831159.d.html\"]",
                "comment_reply": "0",
                "comment_show": "0",
                "comment_total": "0",
                "praise": "0",
                "dispraise": "0",
                "hqChart": "{\"stockCharts\":\"no\",\"stockCode\":\"\",\"stockMarket\":\"\",\"mulStockChart\":\"\",\"isStaticStock\":\"\"}",
                "icons": "",
                "is_cre_manual": "0"
            },
            {
                "icons": "",
                "is_cre_manual": "0",
                "hqChart": "{\"stockCharts\":\"min\",\"stockCode\":\"000001\",\"stockMarket\":\"sh\",\"mulStockChart\":\"\",\"isStaticStock\":\"\"}",
                "intime": "1641550110",
                "channelid": "31",
                "ctime": "1641518784",
                "mtime": "1641550107",
                "authoruid": "0",
                "level": "2",
                "vid": "0",
                "ipad_vid": "0",
                "video_time_length": "0",
                "categoryid": "1",
                "mediaid": "0",
                "subjectid": "149405",
                "templateid": "0",
                "productid": "0",
                "ext_0": "0",
                "ext_1": "0",
                "ext_2": "0",
                "ext_3": "0",
                "ext_4": "0",
                "docid": "comos:kyakumx8820862",
                "url": "https://finance.sina.com.cn/stock/jsy/2022-01-07/doc-ikyakumx8820862.shtml",
                "urls": "[\"https:\\/\\/finance.sina.com.cn\\/stock\\/jsy\\/2022-01-07\\/doc-ikyakumx8820862.shtml\"]",
                "wapurl": "https://finance.sina.cn/stock/dpps/2022-01-07/detail-ikyakumx8820862.d.html",
                "wapurls": "[\"https:\\/\\/finance.sina.cn\\/stock\\/dpps\\/2022-01-07\\/detail-ikyakumx8820862.d.html\",\"http:\\/\\/finance.sina.cn\\/stock\\/dpps\\/2022-01-07\\/detail-ikyakumx8820862.d.html\"]",
                "wapsummary": "",
                "title": "开盘：三大指数集体高开沪指涨0.08% 数字货币板块涨幅居前",
                "stitle": "",
                "summary": "",
                "intro": " 1月7日消息，A股三大指数集体高开，数字货币板块涨幅居前。截至今日开盘，沪指报3588.99点，涨0.08%；深成指报14449.54点，涨0.14%；创指报3137.07点，涨0.31%。",
                "author": "",
                "commentid": "cj:comos-kyakumx8820862:0",
                "video_id": "",
                "keywords": "",
                "media_name": "市场资讯",
                "columnid": "1850,1883,60765",
                "img": {
                    "u": "http://www.sinaimg.cn/cj/2015/1027/U10866P31DT20151027164628.jpg",
                    "w": 400,
                    "h": 300,
                    "t": ""
                },
                "images": [],
                "lids": "295,750,2509,2517,2519,2544,2666,2671",
                "oid": "489094278",
                "comment_reply": 10,
                "comment_show": 7,
                "comment_total": 26
            },
            {
                "oid": "489063305",
                "docid": "comos:kyakumx8801976",
                "url": "https://finance.sina.com.cn/blockchain/roll/2022-01-07/doc-ikyakumx8801976.shtml",
                "wapurl": "https://finance.sina.cn/blockchain/2022-01-07/detail-ikyakumx8801976.d.html",
                "title": "比特币大跌也难掩多头热情 坚持看涨至10万美元",
                "stitle": "",
                "summary": "",
                "wapsummary": "",
                "intro": "智通财经APP获悉，在美联储公布去年12月会议纪要后，比特币的价格在周四一度出现大幅下跌。尽管如此，多头们仍然觉得，该加密货币可以在今年的某个时候达到10万美元的水平...",
                "ctime": "1641512705",
                "mtime": "1641512721",
                "intime": "1641512724",
                "author": "",
                "authoruid": "0",
                "level": "2",
                "img": {
                    "u": "http://n.sinaimg.cn/finance/transform/306/w1218h688/20220107/1fbe-10eaf52fd95518c5fba6752de5266029.jpg",
                    "w": "1218",
                    "h": "688",
                    "t": ""
                },
                "images": [
                    {
                        "u": "http://n.sinaimg.cn/sinakd20220107s/306/w1218h688/20220107/3933-963e5818bd11187b44fb52af333731b7.jpg",
                        "w": "1218",
                        "h": "688",
                        "t": ""
                    }
                ],
                "commentid": "cj:comos-kyakumx8801976:0",
                "vid": "0",
                "ipad_vid": "0",
                "keywords": "",
                "categoryid": "1",
                "channelid": "31",
                "mediaid": "0",
                "columnid": "60765,60808,60810",
                "subjectid": "",
                "templateid": "0",
                "productid": "0",
                "lids": "2519,2544,2666,2667,2668",
                "mlids": "",
                "ext_0": "0",
                "ext_1": "0",
                "ext_2": "0",
                "ext_3": "0",
                "ext_4": "0",
                "ext": "1",
                "media_name": "市场资讯",
                "video_id": "0",
                "video_time_length": "0",
                "urls": "[\"https:\\/\\/finance.sina.com.cn\\/blockchain\\/roll\\/2022-01-07\\/doc-ikyakumx8801976.shtml\"]",
                "wapurls": "[\"https:\\/\\/finance.sina.cn\\/blockchain\\/2022-01-07\\/detail-ikyakumx8801976.d.html\",\"http:\\/\\/finance.sina.cn\\/blockchain\\/2022-01-07\\/detail-ikyakumx8801976.d.html\"]",
                "comment_reply": "9",
                "comment_show": "9",
                "comment_total": "21",
                "praise": "0",
                "dispraise": "0",
                "hqChart": "{\"stockCharts\":\"\\u6bd4\\u7279\\u5e01k\\u7ebf\\u56fe\",\"stockCode\":\"btcbtcdollar\",\"stockMarket\":\"no\",\"mulStockChart\":\"\",\"isStaticStock\":\"\"}",
                "icons": "",
                "is_cre_manual": "0"
            },
            {
                "oid": "489063561",
                "docid": "comos:kyakumx8790198",
                "url": "https://finance.sina.com.cn/blockchain/roll/2022-01-07/doc-ikyakumx8790198.shtml",
                "wapurl": "https://finance.sina.cn/forex/hsxw/2022-01-07/detail-ikyakumx8790198.d.html",
                "title": "数字人民币（试点版）APP来了、成都入围试点 市民可下载尝鲜",
                "stitle": "",
                "summary": "",
                "wapsummary": "",
                "intro": "四川日报  本报讯（四川日报全媒体记者 高杲）数字人民币试点再迎重大进展。1月4日，数字人民币（试点版）APP上架各大安卓应用商店和苹果APP Store。",
                "ctime": "1641506720",
                "mtime": "1641513201",
                "intime": "1641513206",
                "author": "",
                "authoruid": "0",
                "level": "2",
                "img": [],
                "images": [],
                "commentid": "cj:comos-kyakumx8790198:0",
                "vid": "0",
                "ipad_vid": "0",
                "keywords": "数字人民币,APP",
                "categoryid": "1",
                "channelid": "31",
                "mediaid": "0",
                "columnid": "1966,1972,60765,60808,60810",
                "subjectid": "",
                "templateid": "0",
                "productid": "0",
                "lids": "295,1084,2487,2509,2519,2544,2666,2667,2668,2676",
                "mlids": "",
                "ext_0": "0",
                "ext_1": "0",
                "ext_2": "0",
                "ext_3": "0",
                "ext_4": "0",
                "ext": "1",
                "media_name": "媒体滚动",
                "video_id": "0",
                "video_time_length": "0",
                "urls": "[\"https:\\/\\/finance.sina.com.cn\\/blockchain\\/roll\\/2022-01-07\\/doc-ikyakumx8790198.shtml\"]",
                "wapurls": "[\"https:\\/\\/finance.sina.cn\\/forex\\/hsxw\\/2022-01-07\\/detail-ikyakumx8790198.d.html\",\"http:\\/\\/finance.sina.cn\\/forex\\/hsxw\\/2022-01-07\\/detail-ikyakumx8790198.d.html\"]",
                "hqChart": "{\"stockCharts\":\"\\u5916\\u6c47K\\u7ebf\\u56fe\",\"stockCode\":\"USDCNY\",\"stockMarket\":\"\",\"mulStockChart\":\"\",\"isStaticStock\":\"\"}",
                "icons": "",
                "is_cre_manual": "0"
            },
            {
                "mediaid": "0",
                "productid": "0",
                "summary": "",
                "ctime": "1641506460",
                "url": "https://finance.sina.com.cn/blockchain/coin/2022-01-07/doc-ikyamrmz3623300.shtml",
                "author": "",
                "stitle": "",
                "authoruid": "0",
                "wapsummary": "",
                "images": [
                    {
                        "u": "http://n.sinaimg.cn/spider20220107/87/w1080h607/20220107/13b0-552c0cb2701bb2328c627d003ec7470b.jpg",
                        "w": "1080",
                        "h": "607",
                        "t": ""
                    },
                    {
                        "u": "http://n.sinaimg.cn/spider20220107/87/w1080h607/20220107/e65f-9edd55ef1227cf8c7e3f276e1aa61460.jpg",
                        "w": "1080",
                        "h": "607",
                        "t": ""
                    },
                    {
                        "u": "http://n.sinaimg.cn/spider20220107/201/w1080h721/20220107/acf6-af385e3a7e1a022f5bc67d2780ca6104.jpg",
                        "w": "1080",
                        "h": "721",
                        "t": ""
                    },
                    {
                        "u": "http://n.sinaimg.cn/spider20220107/200/w1080h720/20220107/c1f5-f09535c8465b7b3e75556cb2fc907aa1.jpg",
                        "w": "1080",
                        "h": "720",
                        "t": ""
                    },
                    {
                        "u": "http://n.sinaimg.cn/spider20220107/200/w1080h720/20220107/ea10-6ed0cffeeba8fee1506e510aa8e5ed33.jpg",
                        "w": "1080",
                        "h": "720",
                        "t": ""
                    },
                    {
                        "u": "http://n.sinaimg.cn/spider20220107/200/w1080h720/20220107/766d-e710b7224a41e3dce061ded966cdcba7.jpg",
                        "w": "1080",
                        "h": "720",
                        "t": ""
                    }
                ],
                "level": "2",
                "keywords": "数字人民币,国办",
                "mlids": "",
                "wapurl": "https://finance.sina.cn/forex/hsxw/2022-01-07/detail-ikyamrmz3623300.d.html",
                "columnid": "1966,1972,60765,60808",
                "oid": "489063589",
                "img": {
                    "u": "http://n.sinaimg.cn/finance/transform/87/w1080h607/20220107/763c-19a1c4ec7aef950ca6b8666c47d923a9.jpg",
                    "w": "1080",
                    "h": "607",
                    "t": ""
                },
                "subjectid": "",
                "commentid": "cj:comos-kyamrmz3623300:0",
                "ipad_vid": "0",
                "vid": "0",
                "video_id": "0",
                "channelid": "31",
                "intime": "1641513054",
                "video_time_length": "0",
                "categoryid": "1",
                "hqChart": "{\"stockCharts\":\"\\u5916\\u6c47K\\u7ebf\\u56fe\",\"stockCode\":\"USDCNY\",\"stockMarket\":\"\",\"mulStockChart\":\"\",\"isStaticStock\":\"\"}",
                "intro": "央视财经  国务院办公厅近日印发《要素市场化配置综合改革试点总体方案》，推动要素市场化配置改革向纵深发展，一起来看！ 试点布局 围绕推动国家重大战略实施...",
                "is_cre_manual": "0",
                "icons": "",
                "mtime": "1641513051",
                "media_name": "媒体滚动",
                "ext_0": "0",
                "ext_1": "0",
                "title": "国办发文、信息量巨大！涉及户口、企业上市、数字人民币",
                "ext_2": "0",
                "docid": "comos:kyamrmz3623300",
                "ext_3": "0",
                "ext_4": "0",
                "urls": "[\"https:\\/\\/finance.sina.com.cn\\/blockchain\\/coin\\/2022-01-07\\/doc-ikyamrmz3623300.shtml\"]",
                "templateid": "0",
                "lids": "295,1084,2487,2509,2519,2544,2666,2667,2676",
                "wapurls": "[\"https:\\/\\/finance.sina.cn\\/forex\\/hsxw\\/2022-01-07\\/detail-ikyamrmz3623300.d.html\",\"http:\\/\\/finance.sina.cn\\/forex\\/hsxw\\/2022-01-07\\/detail-ikyamrmz3623300.d.html\"]",
                "ext": "1"
            },
            {
                "oid": "489054888",
                "docid": "comos:kyakumx8788909",
                "url": "https://finance.sina.com.cn/stock/usstock/c/2022-01-07/doc-ikyakumx8788909.shtml",
                "wapurl": "https://finance.sina.cn/usstock/mggd/2022-01-07/detail-ikyakumx8788909.d.html",
                "title": "传游戏驿站欲进军NFT和加密货币市场 股价盘后飙升近20%",
                "stitle": "",
                "summary": "",
                "wapsummary": "",
                "intro": "据媒体报道，游戏驿站（GME）计划进军非同质化代币（NFT）和加密数字货币市场。 报道称，游戏驿站计划与两家加密数字货币公司合作，将为视频游戏类NFT产品打造一个市场。",
                "ctime": "1641505506",
                "mtime": "1641509976",
                "intime": "1641509979",
                "author": "",
                "authoruid": "0",
                "level": "2",
                "img": [],
                "images": [
                    {
                        "u": "http://n.sinaimg.cn/finance/transform/59/w550h309/20220107/40ef-2a67e38b4e4a859dfe9f34ef5ef01d31.jpg",
                        "w": "550",
                        "h": "309",
                        "t": ""
                    }
                ],
                "commentid": "cj:comos-kyakumx8788909:0",
                "vid": "0",
                "ipad_vid": "0",
                "keywords": "",
                "categoryid": "1",
                "channelid": "31",
                "mediaid": "0",
                "columnid": "1850,2018,2032,60765",
                "subjectid": "",
                "templateid": "0",
                "productid": "0",
                "lids": "295,747,1083,1084,1131,1134,2509,2516,2517,2518,2519,2544,2666,2671,2672,2676",
                "mlids": "",
                "ext_0": "0",
                "ext_1": "0",
                "ext_2": "0",
                "ext_3": "0",
                "ext_4": "0",
                "ext": "1",
                "media_name": "市场资讯",
                "video_id": "0",
                "video_time_length": "0",
                "urls": "[\"https:\\/\\/finance.sina.com.cn\\/stock\\/usstock\\/c\\/2022-01-07\\/doc-ikyakumx8788909.shtml\"]",
                "wapurls": "[\"https:\\/\\/finance.sina.cn\\/usstock\\/mggd\\/2022-01-07\\/detail-ikyakumx8788909.d.html\",\"http:\\/\\/finance.sina.cn\\/usstock\\/mggd\\/2022-01-07\\/detail-ikyakumx8788909.d.html\"]",
                "comment_reply": "0",
                "comment_show": "0",
                "comment_total": "0",
                "praise": "0",
                "dispraise": "0",
                "hqChart": "{\"stockCharts\":\"\\u7f8e\\u80a1\\u5206\\u65f6\\u56fe\",\"stockCode\":\"GME\",\"stockMarket\":\"us\",\"mulStockChart\":\"\",\"isStaticStock\":\"\"}",
                "icons": "",
                "is_cre_manual": "0"
            },
            {
                "oid": "489063786",
                "docid": "comos:kyamrmz3614063",
                "url": "https://finance.sina.com.cn/blockchain/coin/2022-01-07/doc-ikyamrmz3614063.shtml",
                "wapurl": "https://finance.sina.cn/forex/hsxw/2022-01-07/detail-ikyamrmz3614063.d.html",
                "title": "试点一年有余 看海南如何把数字人民币用起来",
                "stitle": "",
                "summary": "",
                "wapsummary": "",
                "intro": "工人日报 近日，海南海口推出1000万元“数字人民币 椰城嗨购节”红包消费活动。此次活动获得海口市民的积极参与，让市民体验到了不同的支付方式。",
                "ctime": "1641503322",
                "mtime": "1641513319",
                "intime": "1641513322",
                "author": "",
                "authoruid": "0",
                "level": "2",
                "img": [],
                "images": [],
                "commentid": "cj:comos-kyamrmz3614063:0",
                "vid": "0",
                "ipad_vid": "0",
                "keywords": "数字人民币,海口市,海南省",
                "categoryid": "1",
                "channelid": "31",
                "mediaid": "0",
                "columnid": "1966,1972,60765,60808,60810",
                "subjectid": "",
                "templateid": "0",
                "productid": "0",
                "lids": "295,1084,2487,2509,2519,2544,2666,2667,2668,2676",
                "mlids": "",
                "ext_0": "0",
                "ext_1": "0",
                "ext_2": "0",
                "ext_3": "0",
                "ext_4": "0",
                "ext": "1",
                "media_name": "",
                "video_id": "0",
                "video_time_length": "0",
                "urls": "[\"https:\\/\\/finance.sina.com.cn\\/blockchain\\/coin\\/2022-01-07\\/doc-ikyamrmz3614063.shtml\"]",
                "wapurls": "[\"https:\\/\\/finance.sina.cn\\/forex\\/hsxw\\/2022-01-07\\/detail-ikyamrmz3614063.d.html\",\"http:\\/\\/finance.sina.cn\\/forex\\/hsxw\\/2022-01-07\\/detail-ikyamrmz3614063.d.html\"]",
                "hqChart": "{\"stockCharts\":\"\\u5916\\u6c47K\\u7ebf\\u56fe\",\"stockCode\":\"USDCNY\",\"stockMarket\":\"\",\"mulStockChart\":\"\",\"isStaticStock\":\"\"}",
                "icons": "",
                "is_cre_manual": "0"
            },
            {
                "oid": "489060823",
                "docid": "comos:kyakumx8780309",
                "url": "https://finance.sina.com.cn/blockchain/roll/2022-01-07/doc-ikyakumx8780309.shtml",
                "wapurl": "https://finance.sina.cn/forex/hsxw/2022-01-07/detail-ikyakumx8780309.d.html",
                "title": "数字人民币APP与场景扩容“联动”：全量测试阶段开启",
                "stitle": "",
                "summary": "",
                "wapsummary": "",
                "intro": "原标题：数字人民币APP与场景扩容“联动”：全量测试阶段开启 受理环境建设提速 在数字人民币APP（试点版）上架各大应用商店后，其应用场景迅速扩容。",
                "ctime": "1641494894",
                "mtime": "1641511289",
                "intime": "1641511292",
                "author": "",
                "authoruid": "0",
                "level": "2",
                "img": {
                    "u": "http://n.sinaimg.cn/finance/transform/116/w550h366/20211117/9b8b-a170bde66886cee0a9e542dd88b6b8f7.png",
                    "w": "550",
                    "h": "366",
                    "t": ""
                },
                "images": [],
                "commentid": "cj:comos-kyakumx8780309:0",
                "vid": "0",
                "ipad_vid": "0",
                "keywords": "数字人民币,APP,外卖,美团",
                "categoryid": "1",
                "channelid": "31",
                "mediaid": "0",
                "columnid": "1966,1972,60765,60808,60810",
                "subjectid": "",
                "templateid": "0",
                "productid": "0",
                "lids": "295,1084,2487,2509,2519,2544,2666,2667,2668,2676",
                "mlids": "",
                "ext_0": "0",
                "ext_1": "0",
                "ext_2": "0",
                "ext_3": "0",
                "ext_4": "0",
                "ext": "1",
                "media_name": "21世纪经济报道",
                "video_id": "0",
                "video_time_length": "0",
                "urls": "[\"https:\\/\\/finance.sina.com.cn\\/blockchain\\/roll\\/2022-01-07\\/doc-ikyakumx8780309.shtml\"]",
                "wapurls": "[\"https:\\/\\/finance.sina.cn\\/forex\\/hsxw\\/2022-01-07\\/detail-ikyakumx8780309.d.html\",\"http:\\/\\/finance.sina.cn\\/forex\\/hsxw\\/2022-01-07\\/detail-ikyakumx8780309.d.html\"]",
                "comment_reply": "1",
                "comment_show": "1",
                "comment_total": "4",
                "praise": "0",
                "dispraise": "0",
                "hqChart": "{\"stockCharts\":\"\\u5916\\u6c47K\\u7ebf\\u56fe\",\"stockCode\":\"USDCNY\",\"stockMarket\":\"\",\"mulStockChart\":\"\",\"isStaticStock\":\"\"}",
                "icons": "",
                "is_cre_manual": "0"
            }
        ]
    }
}